Front_end/Verilog/top_final.v
// ================= Program Counter =================
module Program_counter(input clk, reset, input [31:0] PC_in, output reg [31:0] PC_out);
    always @(posedge clk or posedge reset)
        if(reset) PC_out <= 0;
        else PC_out <= PC_in;
endmodule

module pc_incr(input [31:0] PC_Form, output [31:0] PC_Next);
    assign PC_Next = PC_Form + 4;
endmodule

// ================= Instruction Memory =================
module Instruction_memory(input clk, input [31:0] read_addr, output reg [31:0] inst_out);
    reg [31:0] inst_memory [0:63];
    initial begin
        // Initialize all to 0
        inst_memory[0] = 32'b00000000000000000000000000000000; // NOP
        // R-type instructions
        inst_memory[1] = 32'b0000000_11001_10000_000_01101_0110011; // add x13,x16,x25 (at PC=4)
        inst_memory[2] = 32'b0100000_00011_01000_000_00101_0110011; // sub x5,x8,x3 (at PC=8)
        inst_memory[3] = 32'b0000000_00011_00010_111_00001_0110011; // and x1,x2,x3 (at PC=12)
        inst_memory[4] = 32'b0000000_00101_00011_110_00100_0110011; // or x4,x3,x5 (at PC=16)
        // I-type instructions
        inst_memory[5] = 32'b000000000011_10101_000_10110_0010011; // addi x22,x21,3 (at PC=20)
        inst_memory[6] = 32'b000000000001_01000_110_01001_0010011; // ori x9,x8,1 (at PC=24)
        // L-type instructions
        inst_memory[7] = 32'b000000001111_00101_010_01000_0000011; // lw x8,15(x5) (at PC=28)
        inst_memory[8] = 32'b000000000011_00011_010_01001_0000011; // lw x9,3(x3) (at PC=32)
        // S-type instructions
        inst_memory[9] = 32'b0000000_01111_00101_010_01100_0100011; // sw x15,12(x5) (at PC=36)
        inst_memory[10] = 32'b0000000_01110_00110_010_01010_0100011; // sw x14,10(x6) (at PC=40)
        // Branch instruction
        inst_memory[11] = 32'h00948663; // beq (at PC=44)
    end
    always @(posedge clk)
        inst_out <= inst_memory[read_addr[7:2]];
endmodule

// ================= Register File =================
module Register_file(input clk, reset, input [4:0] rs1,rs2,rd,
                     input wr_en, input [31:0] wr_data,
                     output [31:0] read_data1, read_data2);
    reg [31:0] RegFile[31:0]; 
    integer k;
    
    always @(posedge clk or posedge reset) begin
        if(reset) begin
            // Initialize registers with test values
            RegFile[0] = 0;   RegFile[1] = 4;   RegFile[2] = 2;   RegFile[3] = 24;
            RegFile[4] = 4;   RegFile[5] = 1;   RegFile[6] = 44;  RegFile[7] = 4;
            RegFile[8] = 2;   RegFile[9] = 1;   RegFile[10] = 23; RegFile[11] = 4;
            RegFile[12] = 90; RegFile[13] = 10; RegFile[14] = 20; RegFile[15] = 30;
            RegFile[16] = 40; RegFile[17] = 50; RegFile[18] = 60; RegFile[19] = 70;
            RegFile[20] = 80; RegFile[21] = 80; RegFile[22] = 90; RegFile[23] = 70;
            RegFile[24] = 60; RegFile[25] = 65; RegFile[26] = 4;  RegFile[27] = 32;
            RegFile[28] = 12; RegFile[29] = 34; RegFile[30] = 5;  RegFile[31] = 10;
        end
        else if(wr_en && rd!=0) 
            RegFile[rd] <= wr_data;
    end
    
    assign read_data1 = (rs1==0) ? 0 : RegFile[rs1];
    assign read_data2 = (rs2==0) ? 0 : RegFile[rs2];
endmodule

// ================= Immediate Generator =================
module Immediate_generation(input [6:0] opcode, input [31:0] instruction, output reg [31:0] immediate_ext);
    always @(*) case(opcode)
        7'b0000011, 7'b0010011: immediate_ext = {{20{instruction[31]}}, instruction[31:20]}; // I-type
        7'b0100011: immediate_ext = {{20{instruction[31]}}, instruction[31:25], instruction[11:7]}; // S-type
        7'b1100011: immediate_ext = {{19{instruction[31]}}, instruction[31], instruction[7], instruction[30:25], instruction[11:8], 1'b0}; // B-type
        default: immediate_ext = 0;
    endcase
endmodule

// ================= Control =================
module Control(input [6:0] instruction,
               output reg branch, mem_rd, mem_to_reg, mem_wr, ALU_src, reg_wr,
               output reg [1:0] ALU_op);
    always @(*) begin
        {ALU_src, mem_to_reg, reg_wr, mem_rd, mem_wr, branch, ALU_op[1], ALU_op[0]} = 8'b0;
        case(instruction)
            7'b0110011: {ALU_src, mem_to_reg, reg_wr, mem_rd, mem_wr, branch, ALU_op[1], ALU_op[0]} = 8'b00100010; // R-type
            7'b0010011: {ALU_src, mem_to_reg, reg_wr, mem_rd, mem_wr, branch, ALU_op[1], ALU_op[0]} = 8'b10100011; // I-type (ADDI, ORI, etc.)
            7'b0000011: {ALU_src, mem_to_reg, reg_wr, mem_rd, mem_wr, branch, ALU_op[1], ALU_op[0]} = 8'b11110000; // LW
            7'b0100011: {ALU_src, mem_to_reg, reg_wr, mem_rd, mem_wr, branch, ALU_op[1], ALU_op[0]} = 8'b10001000; // SW
            7'b1100011: {ALU_src, mem_to_reg, reg_wr, mem_rd, mem_wr, branch, ALU_op[1], ALU_op[0]} = 8'b00000101; // BEQ
        endcase
    end
endmodule

// ================= ALU Control =================
module ALU_control(input [1:0] ALU_op, input fun_7, input [2:0] fun_3, output reg [3:0] Ctrl_out);
    always @(*) case({ALU_op, fun_7, fun_3})
        6'b00_0_000: Ctrl_out = 4'b0010; // add (for load/store)
        6'b01_0_000: Ctrl_out = 4'b0110; // sub (for branch)
        6'b10_0_000: Ctrl_out = 4'b0010; // add (R-type)
        6'b10_1_000: Ctrl_out = 4'b0110; // sub (R-type)
        6'b10_0_111: Ctrl_out = 4'b0000; // and (R-type)
        6'b10_0_110: Ctrl_out = 4'b0001; // or (R-type)
        6'b10_0_100: Ctrl_out = 4'b0011; // xor (R-type)
        6'b11_0_000: Ctrl_out = 4'b0010; // addi (I-type)
        6'b11_0_110: Ctrl_out = 4'b0001; // ori (I-type)
        default: Ctrl_out = 4'b0000;     // and
    endcase
endmodule

// ================= ALU =================
module ALU(input [31:0] A, B, input [3:0] Crtl_in, output reg [31:0] ALU_result, output zero);
    always @(*) case(Crtl_in)
        4'b0000: ALU_result = A & B;
        4'b0001: ALU_result = A | B;
        4'b0010: ALU_result = A + B;
        4'b0011: ALU_result = A ^ B;
        4'b0110: ALU_result = A - B;
        default: ALU_result = 0;
    endcase
    assign zero = (ALU_result == 0);
endmodule

// ================= Data Memory =================
module Data_memory(input clk, reset, mem_wr, mem_rd, input [31:0] wr_data, addr, output [31:0] rd_data);
    reg [31:0] D_memory[63:0]; 
    integer k;
    
    always @(posedge clk or posedge reset) begin
        if(reset) begin
            for(k=0; k<64; k=k+1) 
                D_memory[k] <= 0;
        end
        else if(mem_wr) 
            D_memory[addr[7:2]] <= wr_data;
    end
    
    assign rd_data = mem_rd ? D_memory[addr[7:2]] : 0;
endmodule

// ================= MUX, AND, ADDER =================
// FIXED: Corrected MUX logic - when sel=1, output A; when sel=0, output B
module mux1(input [31:0] A1, B1, input sel1, output [31:0] mux_op1); 
    assign mux_op1 = sel1 ? A1 : B1; 
endmodule

module mux2(input [31:0] A2, B2, input sel2, output [31:0] mux_op2); 
    assign mux_op2 = sel2 ? A2 : B2; 
endmodule

module mux3(input [31:0] A3, B3, input sel3, output [31:0] mux_op3); 
    assign mux_op3 = sel3 ? A3 : B3; 
endmodule

module and1(input branch, zero, output and_out); 
    assign and_out = branch & zero; 
endmodule

module adder(input [31:0] in1, in2, output [31:0] sum_out); 
    assign sum_out = in1 + in2; 
endmodule

// ================= TOP =================
module top_final(input clk, reset);
    wire reg_wire_top, mem_wr_top, mem_rd_top, ALUsrc_top, mem_to_reg_top, branch_top;
    wire zero_top, and_out_top;
    wire [1:0] ALU_op_top;
    wire [3:0] ALU_ctrl_out;
    wire [31:0] Inst_out, read_data1_top, read_data2_top, Ext_imm_top;
    wire [31:0] ALU_result_top, PC_Add_op_top, PC_Add_in_top, adder_op_top;
    wire [31:0] mux1_op_top, mux2_op_top, mux3_op_top, Data_Mem_out_top;

    Program_counter PC(clk, reset, mux2_op_top, PC_Add_in_top);
    pc_incr PC_Adder(PC_Add_in_top, PC_Add_op_top);
    Instruction_memory Inst_Mem(clk, PC_Add_in_top, Inst_out);
    Register_file Reg_file(clk, reset, Inst_out[19:15], Inst_out[24:20], Inst_out[11:7],
                           reg_wire_top, mux3_op_top, read_data1_top, read_data2_top);
    Immediate_generation immediate_gen(Inst_out[6:0], Inst_out, Ext_imm_top);
    Control ctrl_unit(Inst_out[6:0], branch_top, mem_rd_top, mem_to_reg_top,
                      mem_wr_top, ALUsrc_top, reg_wire_top, ALU_op_top);
    ALU_control ALU_ctrl(ALU_op_top, Inst_out[30], Inst_out[14:12], ALU_ctrl_out);
    ALU ALU_top(read_data1_top, mux1_op_top, ALU_ctrl_out, ALU_result_top, zero_top);
    mux1 mux1_top(Ext_imm_top, read_data2_top, ALUsrc_top, mux1_op_top);
    and1 and1_top(branch_top, zero_top, and_out_top);
    adder adder_top(PC_Add_in_top, Ext_imm_top, adder_op_top);
    mux2 mux2_top(adder_op_top, PC_Add_op_top, and_out_top, mux2_op_top);
    Data_memory Data_Mem(clk, reset, mem_wr_top, mem_rd_top, read_data2_top, ALU_result_top, Data_Mem_out_top);
    mux3 mux3_top(Data_Mem_out_top, ALU_result_top, mem_to_reg_top, mux3_op_top);
endmodule

Front_end/Verilog/top_tb.v
//==================== RISC-V Testbench ====================
// File: top_tb.v
// This file should be compiled WITH top_final.v
// Command: vcs top_final.v top_tb.v
//          or: iverilog -o sim top_final.v top_tb.v

module top_tb;
    reg clk;
    reg reset;
    
    // DUT instantiation
    top_final cpu (
        .clk(clk),
        .reset(reset)
    );
    
    // Clock generation - 10 time unit period (5ns high, 5ns low)
    initial begin
        clk = 0;
        forever #5 clk = ~clk;
    end
    
    // Test sequence
    initial begin
        // Waveform dumping for Verdi
        $fsdbDumpfile("riscv.fsdb");
        $fsdbDumpvars(0, top_tb);
        
        // For other simulators, use VCD
        $dumpfile("riscv.vcd");
        $dumpvars(0, top_tb);
        
        $display("\n========================================");
        $display("    RV32I Single-Cycle Processor Test    ");
        $display("========================================\n");
        
        // Apply reset
        reset = 1;
        $display("Time=%0t: Applying reset", $time);
        #15;  // Hold reset for 1.5 clock cycles
        reset = 0;
        $display("Time=%0t: Reset released\n", $time);
        
        // Monitor PC and instruction execution
        $display("Starting instruction execution...\n");
        $monitor("Time=%0t | PC=%0d | Inst=0x%h | ALU_result=%0d | rd=%0d | wr_en=%b", 
                 $time, cpu.PC_Add_in_top, cpu.Inst_out, cpu.ALU_result_top, 
                 cpu.Inst_out[11:7], cpu.reg_wire_top);
        
        // Run for enough cycles to execute all instructions
        #500;
        
        // Disable monitoring before final display
        $monitoroff;
        
        // Final results
        $display("\n========================================");
        $display("       Simulation Finished              ");
        $display("========================================");
        $display("Final PC        = %0d", cpu.PC_Add_in_top);
        $display("Last Instruction = 0x%h", cpu.Inst_out);
        $display("ALU Result      = %0d", cpu.ALU_result_top);
        $display("Zero Flag       = %b", cpu.zero_top);
        $display("Branch Signal   = %b", cpu.branch_top);
        
        // Register file contents
        $display("\n========================================");
        $display("       Register File Contents           ");
        $display("========================================");
        $display("x0  (zero) = %0d", cpu.Reg_file.RegFile[0]);
        $display("x1  (ra)   = %0d", cpu.Reg_file.RegFile[1]);
        $display("x2  (sp)   = %0d", cpu.Reg_file.RegFile[2]);
        $display("x3  (gp)   = %0d", cpu.Reg_file.RegFile[3]);
        $display("x4  (tp)   = %0d", cpu.Reg_file.RegFile[4]);
        $display("x5  (t0)   = %0d (signed: %0d)", cpu.Reg_file.RegFile[5], $signed(cpu.Reg_file.RegFile[5]));
        $display("x6  (t1)   = %0d", cpu.Reg_file.RegFile[6]);
        $display("x7  (t2)   = %0d", cpu.Reg_file.RegFile[7]);
        $display("x8  (s0)   = %0d", cpu.Reg_file.RegFile[8]);
        $display("x9  (s1)   = %0d", cpu.Reg_file.RegFile[9]);
        $display("x10 (a0)   = %0d", cpu.Reg_file.RegFile[10]);
        $display("x13 (a3)   = %0d (Expected: 105)", cpu.Reg_file.RegFile[13]);
        $display("x14 (a4)   = %0d", cpu.Reg_file.RegFile[14]);
        $display("x15 (a5)   = %0d", cpu.Reg_file.RegFile[15]);
        $display("x16 (a6)   = %0d", cpu.Reg_file.RegFile[16]);
        $display("x21 (s5)   = %0d", cpu.Reg_file.RegFile[21]);
        $display("x22 (s6)   = %0d (Expected: 83)", cpu.Reg_file.RegFile[22]);
        $display("x25 (s9)   = %0d", cpu.Reg_file.RegFile[25]);
        
        // Data memory contents (showing relevant locations)
        $display("\n========================================");
        $display("       Data Memory Contents             ");
        $display("========================================");
        $display("Note: Memory addresses are word-aligned");
        $display("Mem[0]  = %0d", cpu.Data_Mem.D_memory[0]);
        $display("Mem[1]  = %0d", cpu.Data_Mem.D_memory[1]);
        $display("Mem[2]  = %0d", cpu.Data_Mem.D_memory[2]);
        $display("Mem[3]  = %0d", cpu.Data_Mem.D_memory[3]);
        $display("Mem[6]  = %0d", cpu.Data_Mem.D_memory[6]);
        $display("Mem[13] = %0d", cpu.Data_Mem.D_memory[13]);
        
        // Test results verification
        $display("\n========================================");
        $display("       Test Results                     ");
        $display("========================================");
        
        if (cpu.Reg_file.RegFile[13] == 105)
            $display("✓ PASS: x13 = 105 (ADD x13,x16,x25 => 40+65)");
        else
            $display("✗ FAIL: x13 = %0d, expected 105", cpu.Reg_file.RegFile[13]);
            
        if (cpu.Reg_file.RegFile[5] == 32'hFFFFFFEA)  // -22 in 2's complement
            $display("✓ PASS: x5 = -22 (SUB x5,x8,x3 => 2-24)");
        else
            $display("✗ FAIL: x5 = %0d, expected -22", $signed(cpu.Reg_file.RegFile[5]));
            
        if (cpu.Reg_file.RegFile[1] == 0)
            $display("✓ PASS: x1 = 0 (AND x1,x2,x3 => 2&24)");
        else
            $display("✗ FAIL: x1 = %0d, expected 0", cpu.Reg_file.RegFile[1]);
            
        if (cpu.Reg_file.RegFile[4] == 32'hFFFFFFFE)  // -2
            $display("✓ PASS: x4 = -2 (OR x4,x3,x5 => 24|-22)");
        else
            $display("✗ FAIL: x4 = %0d, expected -2", $signed(cpu.Reg_file.RegFile[4]));
            
        if (cpu.Reg_file.RegFile[22] == 83)
            $display("✓ PASS: x22 = 83 (ADDI x22,x21,3 => 80+3)");
        else
            $display("✗ FAIL: x22 = %0d, expected 83", cpu.Reg_file.RegFile[22]);
            
        if (cpu.Reg_file.RegFile[9] == 3)
            $display("✓ PASS: x9 = 3 (ORI x9,x8,1 => 2|1)");
        else
            $display("✗ FAIL: x9 = %0d, expected 3", cpu.Reg_file.RegFile[9]);
        
        $display("\n========================================\n");
        
        $finish;
    end
    
    // Timeout watchdog
    initial begin
        #1000;
        $display("\n⚠ WARNING: Simulation timeout at %0t", $time);
        $finish;
    end
    
endmodule

Front_end/riscv.vcd
$date
	Wed Jan 21 11:19:50 2026
$end

$version
	Synopsys VCS version W-2024.09-SP2_Full64
$end

$timescale
	1ps
$end

$comment Csum: 1 b714fd1fd33fb32a $end


$scope module top_tb $end
$var reg 1 ! clk $end
$var reg 1 " reset $end

$scope module cpu $end
$var wire 1 # reg_wire_top $end
$var wire 1 $ branch_top $end
$var wire 1 % zero_top $end
$var wire 32 & Inst_out [31:0] $end
$var wire 32 ' ALU_result_top [31:0] $end
$var wire 32 ( PC_Add_in_top [31:0] $end
$var wire 1 ) clk $end
$var wire 1 * reset $end
$var wire 1 + mem_wr_top $end
$var wire 1 , mem_rd_top $end
$var wire 1 - ALUsrc_top $end
$var wire 1 . mem_to_reg_top $end
$var wire 1 / and_out_top $end
$var wire 2 0 ALU_op_top [1:0] $end
$var wire 4 1 ALU_ctrl_out [3:0] $end
$var wire 32 2 read_data1_top [31:0] $end
$var wire 32 3 read_data2_top [31:0] $end
$var wire 32 4 Ext_imm_top [31:0] $end
$var wire 32 5 PC_Add_op_top [31:0] $end
$var wire 32 6 adder_op_top [31:0] $end
$var wire 32 7 mux1_op_top [31:0] $end
$var wire 32 8 mux2_op_top [31:0] $end
$var wire 32 9 mux3_op_top [31:0] $end
$var wire 32 : Data_Mem_out_top [31:0] $end

$scope module PC $end
$var wire 1 ) clk $end
$var wire 1 * reset $end
$var wire 32 8 PC_in [31:0] $end
$var reg 32 ; PC_out [31:0] $end
$upscope $end


$scope module PC_Adder $end
$var wire 32 ( PC_Form [31:0] $end
$var wire 32 5 PC_Next [31:0] $end
$upscope $end


$scope module Inst_Mem $end
$var wire 1 ) clk $end
$var wire 32 ( read_addr [31:0] $end
$var reg 32 < inst_out [31:0] $end
$upscope $end


$scope module Reg_file $end
$var wire 1 ) clk $end
$var wire 1 * reset $end
$var wire 5 = rs1 [4:0] $end
$var wire 5 > rs2 [4:0] $end
$var wire 5 ? rd [4:0] $end
$var wire 1 # wr_en $end
$var wire 32 9 wr_data [31:0] $end
$var wire 32 2 read_data1 [31:0] $end
$var wire 32 3 read_data2 [31:0] $end
$var integer 32 @ k $end
$upscope $end


$scope module immediate_gen $end
$var wire 7 A opcode [6:0] $end
$var wire 32 & instruction [31:0] $end
$var reg 32 B immediate_ext [31:0] $end
$upscope $end


$scope module ctrl_unit $end
$var wire 7 C instruction [6:0] $end
$var reg 1 D branch $end
$var reg 1 E mem_rd $end
$var reg 1 F mem_to_reg $end
$var reg 1 G mem_wr $end
$var reg 1 H ALU_src $end
$var reg 1 I reg_wr $end
$var reg 2 J ALU_op [1:0] $end
$upscope $end


$scope module ALU_ctrl $end
$var wire 2 0 ALU_op [1:0] $end
$var wire 1 K fun_7 $end
$var wire 3 L fun_3 [2:0] $end
$var reg 4 M Ctrl_out [3:0] $end
$upscope $end


$scope module ALU_top $end
$var wire 32 2 A [31:0] $end
$var wire 32 7 B [31:0] $end
$var wire 4 1 Crtl_in [3:0] $end
$var reg 32 N ALU_result [31:0] $end
$var wire 1 % zero $end
$upscope $end


$scope module mux1_top $end
$var wire 32 4 A1 [31:0] $end
$var wire 32 3 B1 [31:0] $end
$var wire 1 - sel1 $end
$var wire 32 7 mux_op1 [31:0] $end
$upscope $end


$scope module and1_top $end
$var wire 1 $ branch $end
$var wire 1 % zero $end
$var wire 1 / and_out $end
$upscope $end


$scope module adder_top $end
$var wire 32 ( in1 [31:0] $end
$var wire 32 4 in2 [31:0] $end
$var wire 32 6 sum_out [31:0] $end
$upscope $end


$scope module mux2_top $end
$var wire 32 6 A2 [31:0] $end
$var wire 32 5 B2 [31:0] $end
$var wire 1 / sel2 $end
$var wire 32 8 mux_op2 [31:0] $end
$upscope $end


$scope module Data_Mem $end
$var wire 1 ) clk $end
$var wire 1 * reset $end
$var wire 1 + mem_wr $end
$var wire 1 , mem_rd $end
$var wire 32 3 wr_data [31:0] $end
$var wire 32 ' addr [31:0] $end
$var wire 32 : rd_data [31:0] $end
$var integer 32 O k $end
$upscope $end


$scope module mux3_top $end
$var wire 32 : A3 [31:0] $end
$var wire 32 ' B3 [31:0] $end
$var wire 1 . sel3 $end
$var wire 32 9 mux_op3 [31:0] $end
$upscope $end

$upscope $end

$upscope $end

$enddefinitions $end

#0
$dumpvars
xH
x-
x/
xD
x$
0!
1*
bxxx L
xK
bxxxxxxx C
xE
x,
xF
x.
xG
x+
bxxxxxxx A
x#
xI
1"
x%
bxxxx 1
bxx J
bxx 0
bxxxxxxxxxxxxxxxxxxxxxxxxxxxxxxxx N
bxxxxxxxxxxxxxxxxxxxxxxxxxxxxxxxx '
bxxxx M
b00000000000000000000000001000000 O
bxxxxxxxxxxxxxxxxxxxxxxxxxxxxxxxx :
bxxxxxxxxxxxxxxxxxxxxxxxxxxxxxxxx 4
bxxxxxxxxxxxxxxxxxxxxxxxxxxxxxxxx &
b00000000000000000000000000000000 (
b00000000000000000000000000000100 5
b00000000000000000000000000000000 ;
bxxxxxxxxxxxxxxxxxxxxxxxxxxxxxxxx 6
bxxxxxxxxxxxxxxxxxxxxxxxxxxxxxxxx B
bxxxxxxxxxxxxxxxxxxxxxxxxxxxxxxxx <
bxxxxxxxxxxxxxxxxxxxxxxxxxxxxxxxx @
bxxxxxxxxxxxxxxxxxxxxxxxxxxxxxxxx 7
bxxxxxxxxxxxxxxxxxxxxxxxxxxxxxxxx 8
bxxxxxxxxxxxxxxxxxxxxxxxxxxxxxxxx 9
bxxxxxxxxxxxxxxxxxxxxxxxxxxxxxxxx 2
bxxxxxxxxxxxxxxxxxxxxxxxxxxxxxxxx 3
bxxxxx =
bxxxxx >
bxxxxx ?
0)
$end
#5000
1!
1)
b00000000000000000000000000000000 <
b00000000000000000000000000000000 &
b00000 =
b00000 >
b00000 ?
b000 L
0K
b0000000 C
b0000000 A
b00000000000000000000000000000000 B
b00000000000000000000000000000000 4
b00000000000000000000000000000000 6
b0000 M
b0000 1
b00 J
b00 0
0D
0$
0/
0G
0+
0E
0,
0I
0#
0F
0.
0H
0-
b00000000000000000000000000000000 3
b00000000000000000000000000000000 2
b00000000000000000000000000000100 8
b00000000000000000000000000000000 N
b00000000000000000000000000000000 '
1%
b0010 M
b0010 1
b00000000000000000000000000000000 :
b00000000000000000000000000000000 7
b00000000000000000000000000000000 9
#10000
0!
0)
#15000
0"
0*
1!
1)
b00000000000000000000000000000100 ;
b00000000000000000000000000000100 (
b00000000000000000000000000001000 5
b00000000000000000000000000000100 6
b00000000000000000000000000001000 8
#20000
0!
0)
#25000
1!
1)
b00000001100110000000011010110011 <
b00000001100110000000011010110011 &
b10000 =
b11001 >
b01101 ?
b0110011 C
b0110011 A
b00000000000000000000000000001000 ;
b00000000000000000000000000001000 (
b00000000000000000000000000001100 5
b00000000000000000000000000001000 6
b10 J
b10 0
1I
1#
b00000000000000000000000001000001 3
b00000000000000000000000000101000 2
b00000000000000000000000000001100 8
b00000000000000000000000001000001 7
b00000000000000000000000001101001 N
b00000000000000000000000001101001 '
0%
b00000000000000000000000001101001 9
#30000
0!
0)
#35000
1!
1)
b01000000001101000000001010110011 <
b01000000001101000000001010110011 &
b01000 =
b00011 >
b00101 ?
1K
b00000000000000000000000000001100 ;
b00000000000000000000000000001100 (
b00000000000000000000000000010000 5
b00000000000000000000000000001100 6
b0110 M
b0110 1
b00000000000000000000000000011000 3
b00000000000000000000000000000010 2
b00000000000000000000000000010000 8
b11111111111111111111111111000001 N
b11111111111111111111111111000001 '
b00000000000000000000000000011000 7
b11111111111111111111111111000001 9
b11111111111111111111111111101010 N
b11111111111111111111111111101010 '
b11111111111111111111111111101010 9
#40000
0!
0)
#45000
1!
1)
b00000000001100010111000010110011 <
b00000000001100010111000010110011 &
b00010 =
b00001 ?
b111 L
0K
b00000000000000000000000000010000 ;
b00000000000000000000000000010000 (
b00000000000000000000000000010100 5
b00000000000000000000000000010000 6
b0000 M
b0000 1
b00000000000000000000000000010100 8
b00000000000000000000000000000000 N
b00000000000000000000000000000000 '
1%
b00000000000000000000000000000000 9
#50000
0!
0)
#55000
1!
1)
b00000000010100011110001000110011 <
b00000000010100011110001000110011 &
b00011 =
b00101 >
b00100 ?
b110 L
b00000000000000000000000000010100 ;
b00000000000000000000000000010100 (
b00000000000000000000000000011000 5
b00000000000000000000000000010100 6
b0001 M
b0001 1
b11111111111111111111111111101010 3
b00000000000000000000000000011000 2
b00000000000000000000000000011000 8
b00000000000000000000000000011000 N
b00000000000000000000000000011000 '
0%
b11111111111111111111111111101010 7
b00000000000000000000000000011000 9
b11111111111111111111111111111010 N
b11111111111111111111111111111010 '
b11111111111111111111111111111010 9
#60000
0!
0)
#65000
1!
1)
b00000000001110101000101100010011 <
b00000000001110101000101100010011 &
b10101 =
b00011 >
b10110 ?
b000 L
b0010011 C
b0010011 A
b00000000000000000000000000011000 ;
b00000000000000000000000000011000 (
b00000000000000000000000000011100 5
b00000000000000000000000000011000 6
b00000000000000000000000000000011 B
b00000000000000000000000000000011 4
b00000000000000000000000000011011 6
b0010 M
b0010 1
b11 J
b11 0
1H
1-
b00000000000000000000000000011000 3
b00000000000000000000000001010000 2
b00000000000000000000000000011100 8
b00000000000000000000000000111010 N
b00000000000000000000000000111010 '
b00000000000000000000000000000011 7
b00000000000000000000000000111010 9
b00000000000000000000000001010011 N
b00000000000000000000000001010011 '
b00000000000000000000000001010011 9
#70000
0!
0)
#75000
1!
1)
b00000000000101000110010010010011 <
b00000000000101000110010010010011 &
b01000 =
b00001 >
b01001 ?
b110 L
b00000000000000000000000000011100 ;
b00000000000000000000000000011100 (
b00000000000000000000000000100000 5
b00000000000000000000000000011111 6
b00000000000000000000000000000001 B
b00000000000000000000000000000001 4
b00000000000000000000000000011101 6
b0001 M
b0001 1
b00000000000000000000000000000000 3
b00000000000000000000000000000010 2
b00000000000000000000000000100000 8
b00000000000000000000000000000001 7
b00000000000000000000000000000011 N
b00000000000000000000000000000011 '
b00000000000000000000000000000011 9
#80000
0!
0)
#85000
1!
1)
b00000000111100101010010000000011 <
b00000000111100101010010000000011 &
b00101 =
b01111 >
b01000 ?
b010 L
b0000011 C
b0000011 A
b00000000000000000000000000100000 ;
b00000000000000000000000000100000 (
b00000000000000000000000000100100 5
b00000000000000000000000000100001 6
b00000000000000000000000000001111 B
b00000000000000000000000000001111 4
b00000000000000000000000000101111 6
b0000 M
b0000 1
b00 J
b00 0
1E
1,
1F
1.
b00000000000000000000000000011110 3
b11111111111111111111111111101010 2
b00000000000000000000000000100100 8
b00000000000000000000000000001111 7
b00000000000000000000000000001010 N
b00000000000000000000000000001010 '
b00000000000000000000000000000000 9
#90000
0!
0)
#95000
1!
1)
b00000000001100011010010010000011 <
b00000000001100011010010010000011 &
b00011 =
b00011 >
b01001 ?
b00000000000000000000000000100100 ;
b00000000000000000000000000100100 (
b00000000000000000000000000101000 5
b00000000000000000000000000110011 6
b00000000000000000000000000000011 B
b00000000000000000000000000000011 4
b00000000000000000000000000100111 6
b00000000000000000000000000011000 3
b00000000000000000000000000011000 2
b00000000000000000000000000101000 8
b00000000000000000000000000000011 7
b00000000000000000000000000000000 N
b00000000000000000000000000000000 '
1%
#100000
0!
0)
#105000
1!
1)
b00000000111100101010011000100011 <
b00000000111100101010011000100011 &
b00101 =
b01111 >
b01100 ?
b0100011 C
b0100011 A
b00000000000000000000000000101000 ;
b00000000000000000000000000101000 (
b00000000000000000000000000101100 5
b00000000000000000000000000101011 6
b00000000000000000000000000001100 B
b00000000000000000000000000001100 4
b00000000000000000000000000110100 6
1G
1+
0E
0,
0I
0#
0F
0.
b00000000000000000000000000011110 3
b11111111111111111111111111101010 2
b00000000000000000000000000101100 8
b00000000000000000000000000001100 7
b00000000000000000000000000001000 N
b00000000000000000000000000001000 '
0%
b00000000000000000000000000001000 9
#110000
0!
0)
#115000
1!
1)
b00000000111000110010010100100011 <
b00000000111000110010010100100011 &
b00110 =
b01110 >
b01010 ?
b00000000000000000000000000101100 ;
b00000000000000000000000000101100 (
b00000000000000000000000000110000 5
b00000000000000000000000000111000 6
b00000000000000000000000000001010 B
b00000000000000000000000000001010 4
b00000000000000000000000000110110 6
b00000000000000000000000000010100 3
b00000000000000000000000000101100 2
b00000000000000000000000000110000 8
b00000000000000000000000000001010 7
#120000
0!
0)
#125000
1!
1)
b00000000100101001000011001100011 <
b00000000100101001000011001100011 &
b01001 =
b01001 >
b01100 ?
b000 L
b1100011 C
b1100011 A
b00000000000000000000000000110000 ;
b00000000000000000000000000110000 (
b00000000000000000000000000110100 5
b00000000000000000000000000111010 6
b00000000000000000000000000001100 B
b00000000000000000000000000001100 4
b00000000000000000000000000111100 6
b0010 M
b0010 1
b01 J
b01 0
1D
1$
0G
0+
0H
0-
b00000000000000000000000000000000 3
b00000000000000000000000000000000 2
b00000000000000000000000000110100 8
b00000000000000000000000000000000 7
b00000000000000000000000000000000 N
b00000000000000000000000000000000 '
1%
1/
b0110 M
b0110 1
b00000000000000000000000000000000 9
b00000000000000000000000000111100 8
#130000
0!
0)
#135000
1!
1)
bxxxxxxxxxxxxxxxxxxxxxxxxxxxxxxxx <
bxxxxxxxxxxxxxxxxxxxxxxxxxxxxxxxx &
bxxxxx =
bxxxxx >
bxxxxx ?
bxxx L
xK
bxxxxxxx C
bxxxxxxx A
b00000000000000000000000000111100 ;
b00000000000000000000000000111100 (
b00000000000000000000000001000000 5
b00000000000000000000000001001000 6
b00000000000000000000000000000000 B
b00000000000000000000000000000000 4
b00000000000000000000000000111100 6
b0000 M
b0000 1
b00 J
b00 0
0D
0$
0/
bxxxxxxxxxxxxxxxxxxxxxxxxxxxxxxxx 3
bxxxxxxxxxxxxxxxxxxxxxxxxxxxxxxxx 2
b00000000000000000000000001000000 8
bxxxxxxxxxxxxxxxxxxxxxxxxxxxxxxxx 7
bxxxxxxxxxxxxxxxxxxxxxxxxxxxxxxxx N
bxxxxxxxxxxxxxxxxxxxxxxxxxxxxxxxx '
x%
bxxxxxxxxxxxxxxxxxxxxxxxxxxxxxxxx 9
#140000
0!
0)
#145000
1!
1)
b00000000000000000000000001000000 ;
b00000000000000000000000001000000 (
b00000000000000000000000001000100 5
b00000000000000000000000001000000 6
b00000000000000000000000001000100 8
#150000
0!
0)
#155000
1!
1)
b00000000000000000000000001000100 ;
b00000000000000000000000001000100 (
b00000000000000000000000001001000 5
b00000000000000000000000001000100 6
b00000000000000000000000001001000 8
#160000
0!
0)
#165000
1!
1)
b00000000000000000000000001001000 ;
b00000000000000000000000001001000 (
b00000000000000000000000001001100 5
b00000000000000000000000001001000 6
b00000000000000000000000001001100 8
#170000
0!
0)
#175000
1!
1)
b00000000000000000000000001001100 ;
b00000000000000000000000001001100 (
b00000000000000000000000001010000 5
b00000000000000000000000001001100 6
b00000000000000000000000001010000 8
#180000
0!
0)
#185000
1!
1)
b00000000000000000000000001010000 ;
b00000000000000000000000001010000 (
b00000000000000000000000001010100 5
b00000000000000000000000001010000 6
b00000000000000000000000001010100 8
#190000
0!
0)
#195000
1!
1)
b00000000000000000000000001010100 ;
b00000000000000000000000001010100 (
b00000000000000000000000001011000 5
b00000000000000000000000001010100 6
b00000000000000000000000001011000 8
#200000
0!
0)
